monico/__init__.py
monico/__main__.py
monico/bootstrap.py
monico/config.py
monico/utils.py
monico/cli/__init__.py
monico/cli/create.py
monico/cli/delete.py
monico/cli/list.py
monico/cli/run.py
monico/cli/run_manager.py
monico/cli/run_worker.py
monico/cli/setup.py
monico/cli/status.py
monico/cli/utils.py
monico/cli/version.py
monico/core/__init__.py
monico/core/app.py
monico/core/manager.py
monico/core/monitor.py
monico/core/probe.py
monico/core/storage.py
monico/core/task.py
monico/core/worker.py
monico/storage/__init__.py
monico/storage/common.py
monico/storage/pg.py
monico/storage/sqlite.py
monico-0.1.dev1.dist-info/LICENSE.txt
monico-0.1.dev1.dist-info/METADATA
monico-0.1.dev1.dist-info/WHEEL
monico-0.1.dev1.dist-info/entry_points.txt
monico-0.1.dev1.dist-info/top_level.txt
monico-0.1.dev1.dist-info/RECORD
