Metadata-Version: 2.1
Name: monico
Version: 0.1.dev1
Summary: Monico is a simple command-line utility for efficiently monitoring and analyzing the availability of websites.
Author-email: Andrew Savchyn <dev@scorpil.com>
License: MIT License
Keywords: monitoring,uptime,networking,web,http,status-check
Classifier: Development Status :: 3 - Alpha
Classifier: Intended Audience :: Developers
Classifier: License :: OSI Approved :: MIT License
Classifier: Programming Language :: Python
Classifier: Programming Language :: Python :: 3
Classifier: Programming Language :: Python :: 3.11
Classifier: Topic :: Internet :: WWW/HTTP
Classifier: Topic :: System :: Monitoring
Classifier: Topic :: System :: Networking :: Monitoring
Requires-Python: >=3.11
License-File: LICENSE.txt
Requires-Dist: aiohttp ==3.9.0
Requires-Dist: aiodns ==3.1.1
Requires-Dist: click ==8.1.7
Requires-Dist: toml ==0.10.2
Requires-Dist: rich ==13.6.0
Provides-Extra: dev
Requires-Dist: black ==23.11.0 ; extra == 'dev'
Requires-Dist: pytest ==7.4.3 ; extra == 'dev'
Requires-Dist: pytest-cov ==4.1.0 ; extra == 'dev'
Requires-Dist: pytest-asyncio ==0.21.1 ; extra == 'dev'
Requires-Dist: aioresponses ==0.7.6 ; extra == 'dev'
Provides-Extra: postgres
Requires-Dist: psycopg2 ==2.9.9 ; extra == 'postgres'
